{"type": "Feature", "id": 12517800, "geometry": {"type": "Point", "coordinates": [68.683403, 37.383099]}, "properties": {"woe:id": 12517800, "woe:parent_id": 2213331, "woe:name": "Dusti Airport", "woe:placetype": 14, "woe:placetype_name": "Airport", "woe:lang": "ENG", "iso:country": "TJ", "meta:provider": ["geoplanet:7.3.1", "geoplanet:7.3.2", "geoplanet:7.4.0", "geoplanet:7.4.1", "geoplanet:7.5.1", "geoplanet:7.5.2", "geoplanet:7.6.0", "geoplanet:7.8.1", "geoplanet:7.9.0", "geoplanet:7.10.0", "geoplanet:8.0.0", "woeplanet:8.0.0"], "meta:indexed": "2020-08-20T21:03:35.211905", "meta:updated": "2020-10-14T11:28:19.886490", "woe:hierarchy": {"continent": 24865671, "country": 23424961, "town": 0, "planet": 1, "county": 0, "suburb": 0, "state": 20070295, "region": 0, "localadmin": 0}, "woe:timezone_id": 28350825, "woe:hash": "tw8udvmsr69p", "woe:centroid": [68.683403, 37.383099], "geom:latitude": 37.383099, "geom:longitude": 68.683403, "geom:hash": "tw8udvmsr69p", "woe:latitude": 37.383099, "geom:centroid": [68.683403, 37.383099], "woe:longitude": 68.683403, "woe:repo": "woeplanet-airport-tj", "geom:area": 0.0, "woe:scale": 19}}