{"type": "Feature", "id": 12517801, "properties": {"woe:id": 12517801, "woe:parent_id": 2212021, "woe:name": "Dzhirgatal Airport", "woe:placetype": 14, "woe:placetype_name": "Airport", "woe:lang": "ENG", "iso:country": "TJ", "meta:provider": ["geoplanet:7.3.1", "geoplanet:7.3.2", "geoplanet:7.4.0", "geoplanet:7.4.1", "geoplanet:7.5.1", "geoplanet:7.5.2", "geoplanet:7.6.0", "geoplanet:7.8.1", "geoplanet:7.9.0", "geoplanet:7.10.0", "geoplanet:8.0.0", "woeplanet:8.0.0"], "meta:indexed": "2020-08-20T21:03:35.212573", "meta:updated": "2020-08-22T02:53:19.841112", "woe:hierarchy": {"continent": 24865671, "country": 23424961, "town": 0, "planet": 1, "county": 0, "suburb": 0, "state": 20070297, "region": 0, "localadmin": 0}, "woe:timezone_id": 28350825, "woe:hash": "twfxht7xhzxr", "woe:centroid": [71.218399, 39.229301], "geom:latitude": 39.229301, "geom:longitude": 71.218399, "geom:hash": "twfxht7xhzxr", "woe:latitude": 39.229301, "geom:centroid": [71.218399, 39.229301], "woe:longitude": 71.218399, "woe:repo": "woeplanet-airport-tj"}, "geometry": {"coordinates": [71.218399, 39.229301], "type": "Point"}}