{"type": "Feature", "id": 12517820, "properties": {"woe:id": 12517820, "woe:parent_id": 2212801, "woe:name": "Kurgan Tyube North Airport", "woe:placetype": 14, "woe:placetype_name": "Airport", "woe:lang": "ENG", "iso:country": "TJ", "meta:provider": ["geoplanet:7.3.1", "geoplanet:7.3.2", "geoplanet:7.4.0", "geoplanet:7.4.1", "geoplanet:7.5.1", "geoplanet:7.5.2", "geoplanet:7.6.0", "geoplanet:7.8.1", "geoplanet:7.9.0", "geoplanet:7.10.0", "geoplanet:8.0.0", "woeplanet:8.0.0"], "meta:indexed": "2020-08-20T21:03:35.226839", "meta:updated": "2020-08-22T02:53:19.849864", "woe:hierarchy": {"continent": 24865671, "country": 23424961, "town": 0, "planet": 1, "county": 0, "suburb": 0, "state": 20070295, "region": 0, "localadmin": 0}, "woe:timezone_id": 28350825, "woe:hash": "tw8zrmfqfzgj", "woe:centroid": [68.876503, 37.869701], "geom:latitude": 37.869701, "geom:longitude": 68.876503, "geom:hash": "tw8zrmfqfzgj", "woe:latitude": 37.869701, "geom:centroid": [68.876503, 37.869701], "woe:longitude": 68.876503, "woe:repo": "woeplanet-airport-tj"}, "geometry": {"coordinates": [68.876503, 37.869701], "type": "Point"}}