{"type": "Feature", "id": 12517831, "geometry": {"type": "Point", "coordinates": [69.744499, 37.983501]}, "properties": {"woe:id": 12517831, "woe:parent_id": 2212455, "woe:name": "Pushion Poyen Airport", "woe:placetype": 14, "woe:placetype_name": "Airport", "woe:lang": "ENG", "iso:country": "TJ", "meta:provider": ["geoplanet:7.3.1", "geoplanet:7.3.2", "geoplanet:7.4.0", "geoplanet:7.4.1", "geoplanet:7.5.1", "geoplanet:7.5.2", "geoplanet:7.6.0", "geoplanet:7.8.1", "geoplanet:7.9.0", "geoplanet:7.10.0", "geoplanet:8.0.0", "woeplanet:8.0.0"], "meta:indexed": "2020-08-20T21:03:35.234792", "meta:updated": "2020-10-14T11:28:19.872812", "woe:hierarchy": {"continent": 24865671, "country": 23424961, "town": 0, "planet": 1, "county": 0, "suburb": 0, "state": 20070295, "region": 0, "localadmin": 0}, "woe:timezone_id": 28350825, "woe:hash": "twc854dmutgc", "woe:centroid": [69.744499, 37.983501], "geom:latitude": 37.983501, "geom:longitude": 69.744499, "geom:hash": "twc854dmutgc", "woe:latitude": 37.983501, "geom:centroid": [69.744499, 37.983501], "woe:longitude": 69.744499, "woe:repo": "woeplanet-airport-tj", "geom:area": 0.0, "woe:scale": 19}}